radon/__init__.py
radon/__main__.py
radon/complexity.py
radon/metrics.py
radon/raw.py
radon/visitors.py
radon/cli/__init__.py
radon/cli/colors.py
radon/cli/harvest.py
radon/cli/tools.py
radon/contrib/__init__.py
radon/contrib/flake8.py
radon/tests/__init__.py
radon/tests/conftest.py
radon/tests/run.py
radon/tests/test_cli.py
radon/tests/test_cli_colors.py
radon/tests/test_cli_harvest.py
radon/tests/test_cli_tools.py
radon/tests/test_complexity_utils.py
radon/tests/test_complexity_visitor.py
radon/tests/test_halstead.py
radon/tests/test_ipynb.py
radon/tests/test_other_metrics.py
radon/tests/test_raw.py
radon/tests/data/__init__.py
radon/tests/data/no_encoding.py
radon/tests/data/py3unicode.py
radon-6.0.0.dist-info/LICENSE
radon-6.0.0.dist-info/METADATA
radon-6.0.0.dist-info/WHEEL
radon-6.0.0.dist-info/entry_points.txt
radon-6.0.0.dist-info/top_level.txt
radon-6.0.0.dist-info/RECORD
