Metadata-Version: 2.1
Name: radon
Version: 6.0.0
Summary: Code Metrics in Python
Home-page: https://radon.readthedocs.org/
Download-URL: https://pypi.python.org/radon/
Author: Michele Lacchia
Author-email: michelelacchia@gmail.com
License: MIT
Project-URL: Source, https://github.com/rubik/radon
Keywords: static analysis code complexity metrics
Platform: any
Classifier: Development Status :: 5 - Production/Stable
Classifier: Environment :: Console
Classifier: Intended Audience :: Developers
Classifier: License :: OSI Approved :: MIT License
Classifier: Operating System :: OS Independent
Classifier: Programming Language :: Python
Classifier: Programming Language :: Python :: 2
Classifier: Programming Language :: Python :: 2.7
Classifier: Programming Language :: Python :: 3
Classifier: Programming Language :: Python :: 3.6
Classifier: Programming Language :: Python :: 3.7
Classifier: Programming Language :: Python :: 3.8
Classifier: Programming Language :: Python :: 3.9
Classifier: Topic :: Software Development
Classifier: Topic :: Software Development :: Libraries :: Python Modules
Classifier: Topic :: Software Development :: Quality Assurance
Classifier: Topic :: Utilities
License-File: LICENSE
Requires-Dist: mando (<0.8,>=0.6)
Requires-Dist: colorama (==0.4.1) ; python_version <= "3.4"
Requires-Dist: colorama (>=0.4.1) ; python_version > "3.4"
Provides-Extra: toml
Requires-Dist: tomli (>=2.0.1) ; extra == 'toml'
